imagedt/__init__.py
imagedt/caffe/__init__.py
imagedt/caffe/trainer.py
imagedt/caffe/network/__init__.py
imagedt/caffe/optim/__init__.py
imagedt/caffe/tools/__init__.py
imagedt/converters/__init__.py
imagedt/converters/caffe_coreml.py
imagedt/converters/caffe_tfmodel.py
imagedt/converters/tfmodel_lite.py
imagedt/converters/tfrecords.py
imagedt/converters/taffe/__init__.py
imagedt/converters/taffe/errors.py
imagedt/converters/taffe/graph.py
imagedt/converters/taffe/layers.py
imagedt/converters/taffe/shapes.py
imagedt/converters/taffe/transformers.py
imagedt/converters/taffe/caffe/__init__.py
imagedt/converters/taffe/caffe/caffe_pb2.py
imagedt/converters/taffe/caffe/resolver.py
imagedt/converters/taffe/tensorflow/__init__.py
imagedt/converters/taffe/tensorflow/network.py
imagedt/converters/taffe/tensorflow/transformer.py
imagedt/decorator/__init__.py
imagedt/decorator/decorator_time.py
imagedt/dir/__init__.py
imagedt/dir/dir_loop.py
imagedt/file/__init__.py
imagedt/file/file_operate.py
imagedt/file/file_write.py
imagedt/file/parse_annotation.py
imagedt/image/__init__.py
imagedt/image/image_pil.py
imagedt/image/process.py
imagedt/tensorflow/__init__.py
imagedt/tensorflow/trainer.py
imagedt/tensorflow/lite/__init__.py
imagedt/tensorflow/lite/lite_wrapper.py
imagedt/tensorflow/network/__init__.py
imagedt/tensorflow/network/lenet.py
imagedt/tensorflow/network/test_lenet.py
imagedt/tensorflow/optim/__init__.py
imagedt/tensorflow/optim/loss.py
imagedt/tensorflow/tools/DataInterface.py
imagedt/tensorflow/tools/Records.py
imagedt/tensorflow/tools/__init__.py
imagedt/tensorflow/tools/data_provider.py
imagedt/tensorflow/tools/dataset_util.py
imagedt/tensorflow/tools/tfmodel_wrapper.py
imagedt/tensorflow/tools/tfrecords.py
imagedt/tools/__init__.py
imagedt/tools/com_tools.py
imagedt/tools/pdf.py
imagedt/tools/plot_curve.py
imagedt/tools/metrics/__init__.py
imagedt/tools/metrics/detect_eval.py
imagedt-0.5.0.dist-info/METADATA
imagedt-0.5.0.dist-info/RECORD
imagedt-0.5.0.dist-info/WHEEL
imagedt-0.5.0.dist-info/top_level.txt
