Metadata-Version: 2.1
Name: imagedt
Version: 0.5.0
Summary: a python lib for neural networks, file and image processing etc. 
Home-page: https://github.com/hanranCode/ImageDT
Author: pytorch_fans11
Author-email: zhengyzms@163.com
License: Apache License 2.0
Keywords: imagedt
Platform: any
